charon_vna/__init__.py
charon_vna/_version.py
charon_vna/cli.py
charon_vna/config_default.json
charon_vna/config_default.py
charon_vna/gui.py
charon_vna/gui_helpers.py
charon_vna/io_.py
charon_vna/plots.py
charon_vna/pluto_example.py
charon_vna/util.py
charon_vna/vna.py
charon_vna-0.2.0.dist-info/METADATA
charon_vna-0.2.0.dist-info/WHEEL
charon_vna-0.2.0.dist-info/entry_points.txt
charon_vna-0.2.0.dist-info/top_level.txt
charon_vna-0.2.0.dist-info/RECORD
