Metadata-Version: 2.2
Name: charon_vna
Version: 0.2.0
Summary: RF Network Analyzer based on the Pluto SDR
Author-email: Brendan Haines <brendan.haines@gmail.com>
License: MIT License
Project-URL: homepage, https://pypi.org/project/charon-vna/
Project-URL: repository, https://git.brendanhaines.com/brendanhaines/charon_vna
Classifier: Programming Language :: Python :: 3
Requires-Python: >=3
Requires-Dist: numpy
Requires-Dist: scipy
Requires-Dist: scikit-rf
Requires-Dist: xarray
Requires-Dist: zarr
Requires-Dist: pylibiio
Requires-Dist: pyadi-iio
Requires-Dist: click
Requires-Dist: matplotlib
Requires-Dist: pyside6
